MANIFEST.in
README.rst
setup.py
flask_now/__init__.py
flask_now/now.py
flask_now.egg-info/PKG-INFO
flask_now.egg-info/SOURCES.txt
flask_now.egg-info/dependency_links.txt
flask_now.egg-info/entry_points.txt
flask_now.egg-info/not-zip-safe
flask_now.egg-info/top_level.txt
flask_now/templates/__init__.py
flask_now/templates/blueprints/run.py
flask_now/templates/blueprints/project/__init__.py
flask_now/templates/blueprints/project/config.py
flask_now/templates/blueprints/project/models.py
flask_now/templates/blueprints/project/blueprints/__init__.py
flask_now/templates/blueprints/project/blueprints/index/__init__.py
flask_now/templates/blueprints/project/blueprints/index/controller.py
flask_now/templates/blueprints/project/blueprints/index/forms.py
flask_now/templates/blueprints/project/static/css/main.css
flask_now/templates/blueprints/project/static/js/script.js
flask_now/templates/blueprints/project/templates/index.html
flask_now/templates/simple/config.py
flask_now/templates/simple/models.py
flask_now/templates/simple/run.py