Metadata-Version: 1.1
Name: flask-now
Version: 0.2.2
Summary: Flask App Generator
Home-page: http://github.com/ozanonurtek/flask-now
Author: Ozan Onur Tek
Author-email: ozanonurtek@gmail.com
License: UNKNOWN
Keywords: extension flask flask-extension flask-build-tool flask_now flask-now app-generator flask-app-generator app generator
Platform: UNKNOWN
Classifier: Environment :: Web Environment
Classifier: Intended Audience :: Developers
Classifier: License :: OSI Approved :: BSD License
Classifier: Operating System :: OS Independent
Classifier: Topic :: Software Development :: Libraries :: Python Modules
Classifier: Topic :: Software Development :: Code Generators
Classifier: Development Status :: 3 - Alpha
Classifier: Framework :: Flask
Classifier: Programming Language :: Python :: 3 :: Only
